pyrogram/__init__.py
pyrogram/client.py
pyrogram/connection/__init__.py
pyrogram/connection/connection.py
pyrogram/connection/transport/__init__.py
pyrogram/connection/transport/tcp/__init__.py
pyrogram/connection/transport/tcp/tcp.py
pyrogram/connection/transport/tcp/tcp_abridged.py
pyrogram/connection/transport/tcp/tcp_abridged_o.py
pyrogram/connection/transport/tcp/tcp_full.py
pyrogram/connection/transport/tcp/tcp_intermediate.py
pyrogram/connection/transport/tcp/tcp_intermediate_o.py
pyrogram/crypto/__init__.py
pyrogram/crypto/aes.py
pyrogram/crypto/mtproto.py
pyrogram/crypto/prime.py
pyrogram/crypto/rsa.py
pyrogram/dispatcher.py
pyrogram/emoji.py
pyrogram/enums/__init__.py
pyrogram/enums/auto_name.py
pyrogram/enums/chat_action.py
pyrogram/enums/chat_event_action.py
pyrogram/enums/chat_member_status.py
pyrogram/enums/chat_members_filter.py
pyrogram/enums/chat_type.py
pyrogram/enums/message_entity_type.py
pyrogram/enums/message_media_type.py
pyrogram/enums/message_service_type.py
pyrogram/enums/messages_filter.py
pyrogram/enums/next_code_type.py
pyrogram/enums/parse_mode.py
pyrogram/enums/poll_type.py
pyrogram/enums/sent_code_type.py
pyrogram/enums/user_status.py
pyrogram/errors/__init__.py
pyrogram/errors/exceptions/__init__.py
pyrogram/errors/exceptions/all.py
pyrogram/errors/exceptions/bad_request_400.py
pyrogram/errors/exceptions/flood_420.py
pyrogram/errors/exceptions/forbidden_403.py
pyrogram/errors/exceptions/internal_server_error_500.py
pyrogram/errors/exceptions/not_acceptable_406.py
pyrogram/errors/exceptions/see_other_303.py
pyrogram/errors/exceptions/service_unavailable_503.py
pyrogram/errors/exceptions/unauthorized_401.py
pyrogram/errors/rpc_error.py
pyrogram/file_id.py
pyrogram/filters.py
pyrogram/handlers/__init__.py
pyrogram/handlers/callback_query_handler.py
pyrogram/handlers/chat_join_request_handler.py
pyrogram/handlers/chat_member_updated_handler.py
pyrogram/handlers/chosen_inline_result_handler.py
pyrofork_dev-2.1.8.dev202305201733.dist-info/COPYING
pyrofork_dev-2.1.8.dev202305201733.dist-info/COPYING.lesser
pyrofork_dev-2.1.8.dev202305201733.dist-info/METADATA
pyrofork_dev-2.1.8.dev202305201733.dist-info/WHEEL
pyrofork_dev-2.1.8.dev202305201733.dist-info/RECORD
