Metadata-Version: 2.1
Name: pyrofork-dev
Version: 2.1.8.dev202305201733
Summary: Elegant, modern and asynchronous Telegram MTProto API framework in Python for users and bots
Home-page: https://github.com/Mayuri-Chan/pyrofork
License: LGPL-3.0-or-later
Keywords: telegram,chat,messenger,mtproto,api,client,library,python
Author: Dan
Author-email: 14043624+delivrance@users.noreply.github.com
Requires-Python: >=3.9,<4.0
Classifier: Development Status :: 4 - Beta
Classifier: Intended Audience :: Developers
Classifier: License :: OSI Approved :: GNU Lesser General Public License v3 (LGPLv3)
Classifier: License :: OSI Approved :: GNU Lesser General Public License v3 or later (LGPLv3+)
Classifier: Natural Language :: English
Classifier: Operating System :: OS Independent
Classifier: Programming Language :: Python
Classifier: Programming Language :: Python :: 3
Classifier: Programming Language :: Python :: 3.9
Classifier: Programming Language :: Python :: 3.10
Classifier: Programming Language :: Python :: 3.11
Classifier: Programming Language :: Python :: Implementation
Classifier: Programming Language :: Python :: Implementation :: CPython
Classifier: Programming Language :: Python :: Implementation :: PyPy
Classifier: Topic :: Communications
Classifier: Topic :: Communications :: Chat
Classifier: Topic :: Internet
Classifier: Topic :: Software Development :: Libraries
Classifier: Topic :: Software Development :: Libraries :: Application Frameworks
Classifier: Topic :: Software Development :: Libraries :: Python Modules
Requires-Dist: aiosqlite (<1.0.0)
Requires-Dist: async-pymongo (==0.1.2)
Requires-Dist: pyaes (==1.6.1)
Requires-Dist: pymediainfo (==6.0.1)
Requires-Dist: pymongo (==4.3.3)
Requires-Dist: pysocks (==1.7.1)
Project-URL: Documentation, https://pyrofork.mayuri.my.id
Project-URL: Repository, https://github.com/Mayuri-Chan/pyrofork
